probs_ontology/__init__.py
probs_ontology/additional_info.ttl
probs_ontology/probs.fss
probs_ontology/probs.ttl
probs_ontology/__pycache__/__init__.cpython-37.pyc
probs_ontology/__pycache__/__init__.cpython-38.pyc
probs_ontology/runner/__init__.py
probs_ontology/runner/datasource.py
probs_ontology/runner/namespace.py
probs_ontology/runner/probs_runner.py
probs_ontology/runner/__pycache__/__init__.cpython-37.pyc
probs_ontology/runner/__pycache__/__init__.cpython-38.pyc
probs_ontology/runner/__pycache__/datasource.cpython-37.pyc
probs_ontology/runner/__pycache__/datasource.cpython-38.pyc
probs_ontology/runner/__pycache__/namespace.cpython-37.pyc
probs_ontology/runner/__pycache__/namespace.cpython-38.pyc
probs_ontology/runner/__pycache__/probs_runner.cpython-37.pyc
probs_ontology/runner/__pycache__/probs_runner.cpython-38.pyc
probs_ontology/runner/__pycache__/rdfox_inputs.cpython-37.pyc
probs_ontology/runner/__pycache__/run_in_dir.cpython-37.pyc
probs_ontology/runner/__pycache__/run_rdfox.cpython-37.pyc
probs_ontology/scripts/conversion/init.rdfox
probs_ontology/scripts/conversion/master.rdfox
probs_ontology/scripts/conversion/rules.dlog
probs_ontology/scripts/conversion/save_data.rdfox
probs_ontology/scripts/conversion/unit_conversion.dlog
probs_ontology/scripts/conversion/object_composition/pcsc_algorithm.rdfox
probs_ontology/scripts/conversion/object_composition/pcsc_delete_contained.rdfox
probs_ontology/scripts/conversion/object_composition/pcsc_delete_contained_rules.dlog
probs_ontology/scripts/conversion/object_composition/pcsc_infer_observations.dlog
probs_ontology/scripts/conversion/object_composition/pcsc_infer_real.dlog
probs_ontology/scripts/conversion/object_composition/pcsc_main.rdfox
probs_ontology/scripts/conversion/object_composition/pcsc_ordering.dlog
probs_ontology/scripts/conversion/object_composition/pcsc_parallel_world.rdfox
probs_ontology/scripts/conversion/object_composition/pcsc_parallel_world_rules.dlog
probs_ontology-1.5.2.dist-info/METADATA
probs_ontology-1.5.2.dist-info/WHEEL
probs_ontology-1.5.2.dist-info/top_level.txt
probs_ontology-1.5.2.dist-info/RECORD
