Metadata-Version: 2.1
Name: probs-ontology
Version: 1.5.2
Summary: Ontology files, RDFox scripts, and Python runner package for PRObs ontology
Home-page: https://github.com/ukfires/probs-ontology
Author: Stefano Germano, Carla Saunders, Rick Lupton
Author-email: mail@ricklupton.name
License: UNKNOWN
Platform: any
Provides-Extra: docs
Requires-Dist: jupyter-book (<0.11,>=0.10) ; extra == 'docs'
Requires-Dist: rdfox-runner ; extra == 'docs'
Requires-Dist: pandas ; extra == 'docs'
Requires-Dist: importlib-resources ; (python_version < "3.9") and extra == 'docs'
Provides-Extra: runner
Requires-Dist: rdfox-runner ; extra == 'runner'
Requires-Dist: pandas ; extra == 'runner'
Requires-Dist: importlib-resources ; (python_version < "3.9") and extra == 'runner'
Provides-Extra: test
Requires-Dist: pytest ; extra == 'test'
Requires-Dist: rdfox-runner ; extra == 'test'
Requires-Dist: pandas ; extra == 'test'
Requires-Dist: importlib-resources ; (python_version < "3.9") and extra == 'test'
